{
    "title": "Muc-Off Helmet & Visor Cleaning Kit",
    "type": "Maintenance",
    "compatible_helmet_types": [
        "All"
    ],
    "compatible_brands": [
        "Universal"
    ],
    "compatible_helmet_ids": [
        "arai-corsair-x",
        "agv-k6",
        "bell-qualifier-dlx-mips",
        "mt-thunder-3",
        "shoei-rf-1400"
    ],
    "features": [
        "Non-toxic formula",
        "Includes microfiber cloth",
        "Safe for matte and gloss finishes",
        "Safe for Pinlock lenses"
    ],
    "price": {
        "current": 19.99,
        "currency": "USD"
    },
    "description": "<p>Keep your field of vision spotless with our Premium Helmet & Visor Cleaning Kit. The gentle, ammonia-free cleaning solution easily removes bugs, dirt, and road grime without damaging anti-scratch or anti-fog coatings. Paired with a high-quality microfiber cloth, it ensures a streak-free shine every time.</p>",
    "id": "visor-cleaning-kit",
    "entity": "accessory"
}