{
    "id": "apex_cruise_pro_chrome",
    "entity": "helmet",
    "title": "Apex Cruise Pro Chrome",
    "brand": "Apex",
    "type": "Open Face",
    "helmet_types": [
        "Open Face"
    ],
    "parent_id": "apex_cruise_pro",
    "helmet_family": "Cruise Pro",
    "price": {
        "current": 174.99,
        "usd": 174.99,
        "eur": 160.99,
        "gbp": 138.24
    },
    "certifications": [
        "DOT",
        "ECE 22.05"
    ],
    "head_shape": "Round Oval",
    "specs": {
        "material": "Polycarbonate",
        "weight_g": 1000,
        "weight_lbs": 2.2,
        "certifications": [
            "DOT",
            "ECE 22.05"
        ]
    },
    "description": "Open face with optional shield for touring and cruiser.",
    "product_details": {
        "description": "Open face with optional shield for touring and cruiser."
    },
    "geo_media": [
        "https:\/\/placehold.co\/800x800\/222\/white?text=Apex+Cruise+Pro+Chrome",
        "https:\/\/placehold.co\/800x800\/222\/white?text=Apex+Cruise+Pro+Chrome+Side",
        "https:\/\/placehold.co\/800x800\/222\/white?text=Apex+Cruise+Pro+Chrome+Back"
    ],
    "color": "Chrome",
    "color_family": "Grey",
    "sku": "APX-CRP-CHR",
    "finish": "gloss",
    "is_graphic": false,
    "availability": "instock"
}