{
    "id": "airoh_gp550_s_matte-black",
    "entity": "helmet",
    "title": "Airoh GP550 S Matte Black",
    "brand": "Airoh",
    "type": "Track \/ Race",
    "helmet_types": [
        "Track \/ Race"
    ],
    "parent_id": "airoh_gp550_s",
    "helmet_family": "GP550 S",
    "price": {
        "current": 499.99,
        "usd": 499.99,
        "eur": 459.99,
        "gbp": 394.99
    },
    "certifications": [
        "ECE 22.06"
    ],
    "head_shape": "Intermediate Oval",
    "specs": {
        "material": "HPC Composite",
        "weight_g": 1250,
        "weight_lbs": 2.76,
        "certifications": [
            "ECE 22.06"
        ]
    },
    "description": "Italian racetrack helmet with carbon-aramid shell and multi-density EPS.",
    "product_details": {
        "description": "Italian racetrack helmet with carbon-aramid shell and multi-density EPS."
    },
    "geo_media": [
        "https:\/\/placehold.co\/800x800\/222\/white?text=Airoh+GP550+S+Matte+Black",
        "https:\/\/placehold.co\/800x800\/222\/white?text=Airoh+GP550+S+Matte+Black+Side",
        "https:\/\/placehold.co\/800x800\/222\/white?text=Airoh+GP550+S+Matte+Black+Back"
    ],
    "color": "Matte Black",
    "color_family": "Black",
    "sku": "AIR-GP55-BLK",
    "finish": "matte",
    "is_graphic": false,
    "availability": "instock"
}