{
    "id": "arai_contour_x",
    "entity": "helmet",
    "title": "Arai Contour-X",
    "brand": "Arai",
    "type": "Full Face",
    "helmet_family": "Contour-X",
    "price": {
        "current": 749.95,
        "currency": "USD"
    },
    "head_shape": "Intermediate Oval",
    "specs": {
        "material": "PB-cLc2",
        "weight_g": 1550,
        "weight_lbs": 3.42,
        "certifications": [
            "DOT",
            "Snell M2020"
        ]
    },
    "description": "Designed for high-speed touring stability and comfort.",
    "product_details": {
        "description": "Designed for high-speed touring stability and comfort."
    },
    "variants": [
        {
            "id": "arai_contour_x_diamond-black",
            "entity": "helmet",
            "title": "Arai Contour-X Diamond Black",
            "type": "Full Face",
            "parent_id": "arai_contour_x",
            "helmet_family": "Contour-X",
            "head_shape": "Intermediate Oval",
            "color": "Diamond Black",
            "color_family": "Black",
            "sku": "ARA-CONX-BLK",
            "finish": "gloss",
            "is_graphic": false,
            "availability": "instock",
            "description": "Designed for high-speed touring stability and comfort.",
            "product_details": {
                "description": "Designed for high-speed touring stability and comfort."
            },
            "price": {
                "current": 749.95,
                "usd": 749.95,
                "eur": 689.95,
                "gbp": 592.46
            },
            "specs": {
                "material": "PB-cLc2",
                "weight_g": 1550,
                "weight_lbs": 3.42,
                "certifications": [
                    "DOT",
                    "Snell M2020"
                ]
            },
            "geo_media": [
                "https:\/\/placehold.co\/800x800\/222\/white?text=Arai+Contour-X+Diamond+Black",
                "https:\/\/placehold.co\/800x800\/222\/white?text=Arai+Contour-X+Diamond+Black+Side",
                "https:\/\/placehold.co\/800x800\/222\/white?text=Arai+Contour-X+Diamond+Black+Back"
            ],
            "helmet_types": [
                "Full Face"
            ]
        },
        {
            "id": "arai_contour_x_fluorescent-yellow",
            "entity": "helmet",
            "title": "Arai Contour-X Fluorescent Yellow",
            "type": "Full Face",
            "parent_id": "arai_contour_x",
            "helmet_family": "Contour-X",
            "head_shape": "Intermediate Oval",
            "color": "Fluorescent Yellow",
            "color_family": "Yellow",
            "sku": "ARA-CONX-YEL",
            "finish": "gloss",
            "is_graphic": false,
            "availability": "instock",
            "description": "Designed for high-speed touring stability and comfort.",
            "product_details": {
                "description": "Designed for high-speed touring stability and comfort."
            },
            "price": {
                "current": 759.95,
                "usd": 759.95,
                "eur": 699.15,
                "gbp": 600.36
            },
            "specs": {
                "material": "PB-cLc2",
                "weight_g": 1550,
                "weight_lbs": 3.42,
                "certifications": [
                    "DOT",
                    "Snell M2020"
                ]
            },
            "geo_media": [
                "https:\/\/placehold.co\/800x800\/222\/white?text=Arai+Contour-X+Fluorescent+Yellow",
                "https:\/\/placehold.co\/800x800\/222\/white?text=Arai+Contour-X+Fluorescent+Yellow+Side",
                "https:\/\/placehold.co\/800x800\/222\/white?text=Arai+Contour-X+Fluorescent+Yellow+Back"
            ],
            "helmet_types": [
                "Full Face"
            ]
        },
        {
            "id": "arai_contour_x_snake-red",
            "entity": "helmet",
            "title": "Arai Contour-X Snake Red",
            "type": "Full Face",
            "parent_id": "arai_contour_x",
            "helmet_family": "Contour-X",
            "head_shape": "Intermediate Oval",
            "color": "Snake Red",
            "color_family": "Red",
            "sku": "ARA-CONX-SNK",
            "finish": "gloss",
            "is_graphic": true,
            "availability": "instock",
            "description": "Designed for high-speed touring stability and comfort.",
            "product_details": {
                "description": "Designed for high-speed touring stability and comfort."
            },
            "price": {
                "current": 849.95,
                "usd": 849.95,
                "eur": 781.95,
                "gbp": 671.46
            },
            "specs": {
                "material": "PB-cLc2",
                "weight_g": 1550,
                "weight_lbs": 3.42,
                "certifications": [
                    "DOT",
                    "Snell M2020"
                ]
            },
            "geo_media": [
                "https:\/\/placehold.co\/800x800\/222\/white?text=Arai+Contour-X+Snake+Red",
                "https:\/\/placehold.co\/800x800\/222\/white?text=Arai+Contour-X+Snake+Red+Side",
                "https:\/\/placehold.co\/800x800\/222\/white?text=Arai+Contour-X+Snake+Red+Back"
            ],
            "helmet_types": [
                "Full Face"
            ]
        }
    ],
    "geo_media": [
        "https:\/\/placehold.co\/800x800\/222\/white?text=Arai+Contour-X+1",
        "https:\/\/placehold.co\/800x800\/222\/white?text=Arai+Contour-X+2",
        "https:\/\/placehold.co\/800x800\/222\/white?text=Arai+Contour-X+3"
    ]
}