{
    "id": "axor_cliq_grey",
    "entity": "helmet",
    "title": "Axor Cliq Grey",
    "brand": "Axor",
    "type": "Modular",
    "helmet_types": [
        "Modular"
    ],
    "parent_id": "axor_cliq",
    "helmet_family": "Cliq",
    "price": {
        "current": 124.99,
        "usd": 124.99,
        "eur": 114.99,
        "gbp": 98.74
    },
    "certifications": [
        "DOT",
        "ECE 22.05"
    ],
    "head_shape": "Intermediate Oval",
    "specs": {
        "material": "Polycarbonate",
        "weight_g": 1620,
        "weight_lbs": 3.57,
        "certifications": [
            "DOT",
            "ECE 22.05"
        ]
    },
    "description": "Axor flip-up modular with internal sun visor for touring.",
    "product_details": {
        "description": "Axor flip-up modular with internal sun visor for touring."
    },
    "geo_media": [
        "https:\/\/placehold.co\/800x800\/222\/white?text=Axor+Cliq+Grey",
        "https:\/\/placehold.co\/800x800\/222\/white?text=Axor+Cliq+Grey+Side",
        "https:\/\/placehold.co\/800x800\/222\/white?text=Axor+Cliq+Grey+Back"
    ],
    "color": "Grey",
    "color_family": "Grey",
    "sku": "AXR-CLQ-GRE",
    "finish": "matte",
    "is_graphic": false,
    "availability": "instock"
}