{
    "id": "premier_jt5",
    "entity": "helmet",
    "title": "Premier JT5",
    "brand": "Premier",
    "type": "Open Face",
    "helmet_family": "JT5",
    "price": {
        "current": 179.99,
        "currency": "USD"
    },
    "head_shape": "Intermediate Oval",
    "specs": {
        "material": "Polycarbonate",
        "weight_g": 1050,
        "weight_lbs": 2.31,
        "certifications": [
            "ECE 22.06"
        ]
    },
    "description": "Classic cafe racer style with peak and interchangeable visor system.",
    "product_details": {
        "description": "Classic cafe racer style with peak and interchangeable visor system."
    },
    "variants": [
        {
            "id": "premier_jt5_gloss-black",
            "entity": "helmet",
            "title": "Premier JT5 Gloss Black",
            "type": "Open Face",
            "parent_id": "premier_jt5",
            "helmet_family": "JT5",
            "head_shape": "Intermediate Oval",
            "color": "Gloss Black",
            "color_family": "Black",
            "sku": "PRE-JT5-BLK",
            "finish": "gloss",
            "is_graphic": false,
            "availability": "instock",
            "description": "Classic cafe racer style with peak and interchangeable visor system.",
            "product_details": {
                "description": "Classic cafe racer style with peak and interchangeable visor system."
            },
            "price": {
                "current": 179.99,
                "usd": 179.99,
                "eur": 165.59,
                "gbp": 142.19
            },
            "specs": {
                "material": "Polycarbonate",
                "weight_g": 1050,
                "weight_lbs": 2.31,
                "certifications": [
                    "ECE 22.06"
                ]
            },
            "geo_media": [
                "https:\/\/placehold.co\/800x800\/222\/white?text=Premier+JT5+Gloss+Black",
                "https:\/\/placehold.co\/800x800\/222\/white?text=Premier+JT5+Gloss+Black+Side",
                "https:\/\/placehold.co\/800x800\/222\/white?text=Premier+JT5+Gloss+Black+Back"
            ],
            "helmet_types": [
                "Open Face"
            ]
        },
        {
            "id": "premier_jt5_gloss-white",
            "entity": "helmet",
            "title": "Premier JT5 Gloss White",
            "type": "Open Face",
            "parent_id": "premier_jt5",
            "helmet_family": "JT5",
            "head_shape": "Intermediate Oval",
            "color": "Gloss White",
            "color_family": "White",
            "sku": "PRE-JT5-WHI",
            "finish": "gloss",
            "is_graphic": false,
            "availability": "instock",
            "description": "Classic cafe racer style with peak and interchangeable visor system.",
            "product_details": {
                "description": "Classic cafe racer style with peak and interchangeable visor system."
            },
            "price": {
                "current": 179.99,
                "usd": 179.99,
                "eur": 165.59,
                "gbp": 142.19
            },
            "specs": {
                "material": "Polycarbonate",
                "weight_g": 1050,
                "weight_lbs": 2.31,
                "certifications": [
                    "ECE 22.06"
                ]
            },
            "geo_media": [
                "https:\/\/placehold.co\/800x800\/222\/white?text=Premier+JT5+Gloss+White",
                "https:\/\/placehold.co\/800x800\/222\/white?text=Premier+JT5+Gloss+White+Side",
                "https:\/\/placehold.co\/800x800\/222\/white?text=Premier+JT5+Gloss+White+Back"
            ],
            "helmet_types": [
                "Open Face"
            ]
        },
        {
            "id": "premier_jt5_course-red",
            "entity": "helmet",
            "title": "Premier JT5 Course Red",
            "type": "Open Face",
            "parent_id": "premier_jt5",
            "helmet_family": "JT5",
            "head_shape": "Intermediate Oval",
            "color": "Course Red",
            "color_family": "Red",
            "sku": "PRE-JT5-COU",
            "finish": "gloss",
            "is_graphic": true,
            "availability": "instock",
            "description": "Classic cafe racer style with peak and interchangeable visor system.",
            "product_details": {
                "description": "Classic cafe racer style with peak and interchangeable visor system."
            },
            "price": {
                "current": 229.99,
                "usd": 229.99,
                "eur": 211.59,
                "gbp": 181.69
            },
            "specs": {
                "material": "Polycarbonate",
                "weight_g": 1050,
                "weight_lbs": 2.31,
                "certifications": [
                    "ECE 22.06"
                ]
            },
            "geo_media": [
                "https:\/\/placehold.co\/800x800\/222\/white?text=Premier+JT5+Course+Red",
                "https:\/\/placehold.co\/800x800\/222\/white?text=Premier+JT5+Course+Red+Side",
                "https:\/\/placehold.co\/800x800\/222\/white?text=Premier+JT5+Course+Red+Back"
            ],
            "helmet_types": [
                "Open Face"
            ]
        },
        {
            "id": "premier_jt5_street-tc-5",
            "entity": "helmet",
            "title": "Premier JT5 Street TC-5",
            "type": "Open Face",
            "parent_id": "premier_jt5",
            "helmet_family": "JT5",
            "head_shape": "Intermediate Oval",
            "color": "Street TC-5",
            "color_family": "Multi",
            "sku": "PRE-JT5-STR",
            "finish": "matte",
            "is_graphic": true,
            "availability": "instock",
            "description": "Classic cafe racer style with peak and interchangeable visor system.",
            "product_details": {
                "description": "Classic cafe racer style with peak and interchangeable visor system."
            },
            "price": {
                "current": 229.99,
                "usd": 229.99,
                "eur": 211.59,
                "gbp": 181.69
            },
            "specs": {
                "material": "Polycarbonate",
                "weight_g": 1050,
                "weight_lbs": 2.31,
                "certifications": [
                    "ECE 22.06"
                ]
            },
            "geo_media": [
                "https:\/\/placehold.co\/800x800\/222\/white?text=Premier+JT5+Street+TC-5",
                "https:\/\/placehold.co\/800x800\/222\/white?text=Premier+JT5+Street+TC-5+Side",
                "https:\/\/placehold.co\/800x800\/222\/white?text=Premier+JT5+Street+TC-5+Back"
            ],
            "helmet_types": [
                "Open Face"
            ]
        }
    ],
    "geo_media": [
        "https:\/\/placehold.co\/800x800\/222\/white?text=Premier+JT5+1",
        "https:\/\/placehold.co\/800x800\/222\/white?text=Premier+JT5+2",
        "https:\/\/placehold.co\/800x800\/222\/white?text=Premier+JT5+3"
    ]
}