{
    "id": "scorpion_exo_r420_matte-black",
    "entity": "helmet",
    "title": "Scorpion EXO-R420 Matte Black",
    "brand": "Scorpion",
    "type": "Full Face",
    "helmet_types": [
        "Full Face"
    ],
    "parent_id": "scorpion_exo_r420",
    "helmet_family": "EXO-R420",
    "price": {
        "current": 159.95,
        "usd": 159.95,
        "eur": 147.15,
        "gbp": 126.36
    },
    "certifications": [
        "DOT",
        "Snell M2020"
    ],
    "head_shape": "Intermediate Oval",
    "specs": {
        "material": "Polycarbonate",
        "weight_g": 1620,
        "weight_lbs": 3.57,
        "certifications": [
            "DOT",
            "Snell M2020"
        ]
    },
    "description": "Incredible value \u2014 Snell M2020 and DOT certified at an entry-level price.",
    "product_details": {
        "description": "Incredible value \u2014 Snell M2020 and DOT certified at an entry-level price."
    },
    "geo_media": [
        "https:\/\/placehold.co\/800x800\/222\/white?text=Scorpion+EXO-R420+Matte+Black",
        "https:\/\/placehold.co\/800x800\/222\/white?text=Scorpion+EXO-R420+Matte+Black+Side",
        "https:\/\/placehold.co\/800x800\/222\/white?text=Scorpion+EXO-R420+Matte+Black+Back"
    ],
    "color": "Matte Black",
    "color_family": "Black",
    "sku": "SCO-EXOR-BLK",
    "finish": "matte",
    "is_graphic": false,
    "availability": "instock"
}