{
    "id": "studds_glider_d6",
    "entity": "helmet",
    "title": "Studds Glider D6",
    "brand": "Studds",
    "type": "Open Face",
    "helmet_family": "Glider D6",
    "price": {
        "current": 42.99,
        "currency": "USD"
    },
    "head_shape": "Round Oval",
    "specs": {
        "material": "ABS",
        "weight_g": 940,
        "weight_lbs": 2.07,
        "certifications": [
            "DOT"
        ]
    },
    "description": "Open face with adjustable visor for city and short trips.",
    "product_details": {
        "description": "Open face with adjustable visor for city and short trips."
    },
    "variants": [
        {
            "id": "studds_glider_d6_black",
            "entity": "helmet",
            "title": "Studds Glider D6 Black",
            "type": "Open Face",
            "parent_id": "studds_glider_d6",
            "helmet_family": "Glider D6",
            "head_shape": "Round Oval",
            "color": "Black",
            "color_family": "Black",
            "sku": "STU-GLI-BLK",
            "finish": "gloss",
            "is_graphic": false,
            "availability": "instock",
            "description": "Open face with adjustable visor for city and short trips.",
            "product_details": {
                "description": "Open face with adjustable visor for city and short trips."
            },
            "price": {
                "current": 42.99,
                "usd": 42.99,
                "eur": 39.55,
                "gbp": 33.96
            },
            "specs": {
                "material": "ABS",
                "weight_g": 940,
                "weight_lbs": 2.07,
                "certifications": [
                    "DOT"
                ]
            },
            "geo_media": [
                "https:\/\/placehold.co\/800x800\/222\/white?text=Studds+Glider+D6+Black",
                "https:\/\/placehold.co\/800x800\/222\/white?text=Studds+Glider+D6+Black+Side",
                "https:\/\/placehold.co\/800x800\/222\/white?text=Studds+Glider+D6+Black+Back"
            ],
            "helmet_types": [
                "Open Face"
            ]
        },
        {
            "id": "studds_glider_d6_silver",
            "entity": "helmet",
            "title": "Studds Glider D6 Silver",
            "type": "Open Face",
            "parent_id": "studds_glider_d6",
            "helmet_family": "Glider D6",
            "head_shape": "Round Oval",
            "color": "Silver",
            "color_family": "Grey",
            "sku": "STU-GLI-SLV",
            "finish": "gloss",
            "is_graphic": false,
            "availability": "instock",
            "description": "Open face with adjustable visor for city and short trips.",
            "product_details": {
                "description": "Open face with adjustable visor for city and short trips."
            },
            "price": {
                "current": 42.99,
                "usd": 42.99,
                "eur": 39.55,
                "gbp": 33.96
            },
            "specs": {
                "material": "ABS",
                "weight_g": 940,
                "weight_lbs": 2.07,
                "certifications": [
                    "DOT"
                ]
            },
            "geo_media": [
                "https:\/\/placehold.co\/800x800\/222\/white?text=Studds+Glider+D6+Silver",
                "https:\/\/placehold.co\/800x800\/222\/white?text=Studds+Glider+D6+Silver+Side",
                "https:\/\/placehold.co\/800x800\/222\/white?text=Studds+Glider+D6+Silver+Back"
            ],
            "helmet_types": [
                "Open Face"
            ]
        }
    ],
    "geo_media": [
        "https:\/\/placehold.co\/800x800\/222\/white?text=Studds+Glider+D6+1",
        "https:\/\/placehold.co\/800x800\/222\/white?text=Studds+Glider+D6+2",
        "https:\/\/placehold.co\/800x800\/222\/white?text=Studds+Glider+D6+3"
    ]
}