{
    "id": "airoh_gp550_s_gloss-white",
    "entity": "helmet",
    "title": "Airoh GP550 S Gloss White",
    "brand": "Airoh",
    "type": "Track / Race",
    "helmet_types": [
        "Track / Race"
    ],
    "parent_id": "airoh_gp550_s",
    "helmet_family": "GP550 S",
    "price": {
        "current": 499.99,
        "usd": 499.99,
        "eur": 459.99,
        "gbp": 394.99
    },
    "certifications": [
        "ECE 22.06"
    ],
    "head_shape": "Intermediate Oval",
    "specs": {
        "material": "HPC Composite",
        "weight_g": 1250,
        "weight_lbs": 2.76,
        "certifications": [
            "ECE 22.06"
        ],
        "warranty_years": 2,
        "strap_type": "Double D-Ring",
        "shell_sizes_count": 1
    },
    "description": "Italian racetrack helmet with carbon-aramid shell and multi-density EPS.",
    "product_details": {
        "description": "Italian racetrack helmet with carbon-aramid shell and multi-density EPS."
    },
    "geo_media": [
        "https://placehold.co/800x800/222/white?text=Airoh+GP550+S+Gloss+White",
        "https://placehold.co/800x800/222/white?text=Airoh+GP550+S+Gloss+White+Side",
        "https://placehold.co/800x800/222/white?text=Airoh+GP550+S+Gloss+White+Back"
    ],
    "color": "Gloss White",
    "color_family": "White",
    "sku": "AIR-GP55-WHI",
    "finish": "gloss",
    "is_graphic": false,
    "availability": "instock",
    "features_data": {
        "visor": [
            "Pinlock Ready",
            "Optically Correct"
        ]
    },
    "tech_integration": {
        "comms_cutout_type": "Generic Speaker Cutouts"
    }
}