{
    "id": "apex_scope_blue",
    "entity": "helmet",
    "title": "Apex Scope Blue",
    "brand": "Apex",
    "type": "Full Face",
    "helmet_types": [
        "Full Face"
    ],
    "parent_id": "apex_scope",
    "helmet_family": "Scope",
    "price": {
        "current": 249.99,
        "usd": 249.99,
        "eur": 229.99,
        "gbp": 197.49
    },
    "certifications": [
        "DOT",
        "ECE 22.05"
    ],
    "head_shape": "Intermediate Oval",
    "specs": {
        "material": "Polycarbonate",
        "weight_g": 1540,
        "weight_lbs": 3.4,
        "certifications": [
            "DOT",
            "ECE 22.05"
        ],
        "warranty_years": 2,
        "strap_type": "Double D-Ring",
        "shell_sizes_count": 4
    },
    "description": "Sport full face with wide view and good ventilation.",
    "product_details": {
        "description": "Sport full face with wide view and good ventilation."
    },
    "geo_media": [
        "https://placehold.co/800x800/222/white?text=Apex+Scope+Blue",
        "https://placehold.co/800x800/222/white?text=Apex+Scope+Blue+Side",
        "https://placehold.co/800x800/222/white?text=Apex+Scope+Blue+Back"
    ],
    "color": "Blue",
    "color_family": "Blue",
    "sku": "APX-SCP-BLU",
    "finish": "gloss",
    "is_graphic": false,
    "availability": "instock",
    "features_data": {
        "visor": [
            "Pinlock Ready",
            "Optically Correct"
        ]
    },
    "tech_integration": {
        "comms_cutout_type": "Generic Speaker Cutouts",
        "speaker_pocket_depth_mm": 35,
        "cable_management": true,
        "hud_ready": true
    },
    "model_year": 2024,
    "identifiers": {
        "asin": "B08X7Y9Z1A",
        "ean": "8423567890123",
        "mpn": "APEX-BS-FULL-001"
    },
    "safety_intelligence": {
        "homologation_standard": "FIM/FIA/CE EN17097:2019",
        "sharp_rating": 5,
        "rotational_mitigation": true
    },
    "sizing_fit": {
        "fit_notes": "Designed for wide cheekbones; adjustable fit system accommodates head circumferences from 54cm to 62cm.",
        "head_shape": "Intermediate Oval"
    },
    "deep_enriched": true
}