{
    "id": "arai_classic_v_silver-metallic",
    "entity": "helmet",
    "title": "Arai Classic-V Silver Metallic",
    "brand": "Arai",
    "type": "Open Face",
    "helmet_types": [
        "Open Face"
    ],
    "parent_id": "arai_classic_v",
    "helmet_family": "Classic-V",
    "price": {
        "current": 489.95,
        "usd": 489.95,
        "eur": 450.75,
        "gbp": 387.06
    },
    "certifications": [
        "DOT",
        "Snell M2020"
    ],
    "head_shape": "Intermediate Oval",
    "specs": {
        "material": "PB-cLc",
        "weight_g": 1200,
        "weight_lbs": 2.65,
        "certifications": [
            "DOT",
            "Snell M2020"
        ],
        "warranty_years": 1,
        "strap_type": "Double D-Ring",
        "shell_sizes_count": 4
    },
    "description": "Heritage styling with modern Arai protection.",
    "product_details": {
        "description": "Heritage styling with modern Arai protection."
    },
    "geo_media": [
        "https://placehold.co/800x800/222/white?text=Arai+Classic-V+Silver+Metallic",
        "https://placehold.co/800x800/222/white?text=Arai+Classic-V+Silver+Metallic+Side",
        "https://placehold.co/800x800/222/white?text=Arai+Classic-V+Silver+Metallic+Back"
    ],
    "color": "Silver Metallic",
    "color_family": "Grey",
    "sku": "ARA-CLAS-GRE",
    "finish": "gloss",
    "is_graphic": false,
    "availability": "instock",
    "features_data": {
        "visor": [
            "Pinlock Ready",
            "Optically Correct"
        ]
    },
    "tech_integration": {
        "comms_cutout_type": "Generic Speaker Cutouts",
        "speaker_pocket_depth_mm": 8,
        "cable_management": true,
        "hud_ready": false
    },
    "model_year": "2018",
    "identifiers": {
        "asin": "B07Q3K8V5G",
        "ean": "4962100000000",
        "mpn": "AV-CLSV-SILVER-METALLIC"
    },
    "safety_intelligence": {
        "homologation_standard": "ECE 22.05",
        "sharp_rating": 0,
        "rotational_mitigation": "None"
    },
    "sizing_fit": {
        "fit_notes": "Classic-V is designed for a standard head shape with a slightly rounded profile; may require sizing up for elongated heads.",
        "head_shape": "Standard/Rounded"
    },
    "deep_enriched": true
}