{
    "id": "bell_mx_9_adventure_mips",
    "entity": "helmet",
    "title": "Bell MX-9 Adventure MIPS",
    "brand": "Bell",
    "type": "Adventure / Dual Sport",
    "helmet_family": "MX-9 Adventure MIPS",
    "price": {
        "current": 239.95,
        "currency": "USD"
    },
    "head_shape": "Intermediate Oval",
    "specs": {
        "material": "Polycarbonate",
        "weight_g": 1690,
        "weight_lbs": 3.73,
        "certifications": [
            "DOT",
            "ECE 22.05"
        ],
        "warranty_years": 1,
        "strap_type": "Double D-Ring"
    },
    "description": "Highly versatile helmet for exploring the unknown.",
    "product_details": {
        "description": "Highly versatile helmet for exploring the unknown."
    },
    "variants": [
        {
            "id": "bell_mx_9_adventure_mips_gloss-black",
            "entity": "helmet",
            "title": "Bell MX-9 Adventure MIPS Gloss Black",
            "type": "Adventure / Dual Sport",
            "parent_id": "bell_mx_9_adventure_mips",
            "helmet_family": "MX-9 Adventure MIPS",
            "head_shape": "Intermediate Oval",
            "color": "Gloss Black",
            "color_family": "Black",
            "sku": "BEL-MX9A-BLK",
            "finish": "gloss",
            "is_graphic": false,
            "availability": "instock",
            "description": "Highly versatile helmet for exploring the unknown.",
            "product_details": {
                "description": "Highly versatile helmet for exploring the unknown."
            },
            "price": {
                "current": 239.95,
                "usd": 239.95,
                "eur": 220.75,
                "gbp": 189.56
            },
            "specs": {
                "material": "Polycarbonate",
                "weight_g": 1690,
                "weight_lbs": 3.73,
                "certifications": [
                    "DOT",
                    "ECE 22.05"
                ]
            },
            "geo_media": [
                "https://placehold.co/800x800/222/white?text=Bell+MX-9+Adventure+MIPS+Gloss+Black",
                "https://placehold.co/800x800/222/white?text=Bell+MX-9+Adventure+MIPS+Gloss+Black+Side",
                "https://placehold.co/800x800/222/white?text=Bell+MX-9+Adventure+MIPS+Gloss+Black+Back"
            ],
            "helmet_types": [
                "Adventure / Dual Sport"
            ]
        },
        {
            "id": "bell_mx_9_adventure_mips_hi-viz-yellow",
            "entity": "helmet",
            "title": "Bell MX-9 Adventure MIPS Hi-Viz Yellow",
            "type": "Adventure / Dual Sport",
            "parent_id": "bell_mx_9_adventure_mips",
            "helmet_family": "MX-9 Adventure MIPS",
            "head_shape": "Intermediate Oval",
            "color": "Hi-Viz Yellow",
            "color_family": "Yellow",
            "sku": "BEL-MX9A-YEL",
            "finish": "gloss",
            "is_graphic": false,
            "availability": "instock",
            "description": "Highly versatile helmet for exploring the unknown.",
            "product_details": {
                "description": "Highly versatile helmet for exploring the unknown."
            },
            "price": {
                "current": 239.95,
                "usd": 239.95,
                "eur": 220.75,
                "gbp": 189.56
            },
            "specs": {
                "material": "Polycarbonate",
                "weight_g": 1690,
                "weight_lbs": 3.73,
                "certifications": [
                    "DOT",
                    "ECE 22.05"
                ]
            },
            "geo_media": [
                "https://placehold.co/800x800/222/white?text=Bell+MX-9+Adventure+MIPS+Hi-Viz+Yellow",
                "https://placehold.co/800x800/222/white?text=Bell+MX-9+Adventure+MIPS+Hi-Viz+Yellow+Side",
                "https://placehold.co/800x800/222/white?text=Bell+MX-9+Adventure+MIPS+Hi-Viz+Yellow+Back"
            ],
            "helmet_types": [
                "Adventure / Dual Sport"
            ]
        },
        {
            "id": "bell_mx_9_adventure_mips_stripe-tc-5",
            "entity": "helmet",
            "title": "Bell MX-9 Adventure MIPS Stripe TC-5",
            "type": "Adventure / Dual Sport",
            "parent_id": "bell_mx_9_adventure_mips",
            "helmet_family": "MX-9 Adventure MIPS",
            "head_shape": "Intermediate Oval",
            "color": "Stripe TC-5",
            "color_family": "Multi",
            "sku": "BEL-MX9A-STR",
            "finish": "gloss",
            "is_graphic": true,
            "availability": "instock",
            "description": "Highly versatile helmet for exploring the unknown.",
            "product_details": {
                "description": "Highly versatile helmet for exploring the unknown."
            },
            "price": {
                "current": 289.95,
                "usd": 289.95,
                "eur": 266.75,
                "gbp": 229.06
            },
            "specs": {
                "material": "Polycarbonate",
                "weight_g": 1690,
                "weight_lbs": 3.73,
                "certifications": [
                    "DOT",
                    "ECE 22.05"
                ]
            },
            "geo_media": [
                "https://placehold.co/800x800/222/white?text=Bell+MX-9+Adventure+MIPS+Stripe+TC-5",
                "https://placehold.co/800x800/222/white?text=Bell+MX-9+Adventure+MIPS+Stripe+TC-5+Side",
                "https://placehold.co/800x800/222/white?text=Bell+MX-9+Adventure+MIPS+Stripe+TC-5+Back"
            ],
            "helmet_types": [
                "Adventure / Dual Sport"
            ]
        },
        {
            "id": "bell_mx_9_adventure_mips_course-grey",
            "entity": "helmet",
            "title": "Bell MX-9 Adventure MIPS Course Grey",
            "type": "Adventure / Dual Sport",
            "parent_id": "bell_mx_9_adventure_mips",
            "helmet_family": "MX-9 Adventure MIPS",
            "head_shape": "Intermediate Oval",
            "color": "Course Grey",
            "color_family": "Grey",
            "sku": "BEL-MX9A-COU",
            "finish": "matte",
            "is_graphic": true,
            "availability": "instock",
            "description": "Highly versatile helmet for exploring the unknown.",
            "product_details": {
                "description": "Highly versatile helmet for exploring the unknown."
            },
            "price": {
                "current": 289.95,
                "usd": 289.95,
                "eur": 266.75,
                "gbp": 229.06
            },
            "specs": {
                "material": "Polycarbonate",
                "weight_g": 1690,
                "weight_lbs": 3.73,
                "certifications": [
                    "DOT",
                    "ECE 22.05"
                ]
            },
            "geo_media": [
                "https://placehold.co/800x800/222/white?text=Bell+MX-9+Adventure+MIPS+Course+Grey",
                "https://placehold.co/800x800/222/white?text=Bell+MX-9+Adventure+MIPS+Course+Grey+Side",
                "https://placehold.co/800x800/222/white?text=Bell+MX-9+Adventure+MIPS+Course+Grey+Back"
            ],
            "helmet_types": [
                "Adventure / Dual Sport"
            ]
        },
        {
            "id": "bell_mx_9_adventure_mips_solid-tc-3",
            "entity": "helmet",
            "title": "Bell MX-9 Adventure MIPS Solid TC-3",
            "type": "Adventure / Dual Sport",
            "parent_id": "bell_mx_9_adventure_mips",
            "helmet_family": "MX-9 Adventure MIPS",
            "head_shape": "Intermediate Oval",
            "color": "Solid TC-3",
            "color_family": "Multi",
            "sku": "BEL-MX9A-SOL",
            "finish": "matte",
            "is_graphic": true,
            "availability": "instock",
            "description": "Highly versatile helmet for exploring the unknown.",
            "product_details": {
                "description": "Highly versatile helmet for exploring the unknown."
            },
            "price": {
                "current": 289.95,
                "usd": 289.95,
                "eur": 266.75,
                "gbp": 229.06
            },
            "specs": {
                "material": "Polycarbonate",
                "weight_g": 1690,
                "weight_lbs": 3.73,
                "certifications": [
                    "DOT",
                    "ECE 22.05"
                ]
            },
            "geo_media": [
                "https://placehold.co/800x800/222/white?text=Bell+MX-9+Adventure+MIPS+Solid+TC-3",
                "https://placehold.co/800x800/222/white?text=Bell+MX-9+Adventure+MIPS+Solid+TC-3+Side",
                "https://placehold.co/800x800/222/white?text=Bell+MX-9+Adventure+MIPS+Solid+TC-3+Back"
            ],
            "helmet_types": [
                "Adventure / Dual Sport"
            ]
        }
    ],
    "geo_media": [
        "https://placehold.co/800x800/222/white?text=Bell+MX-9+Adventure+MIPS+1",
        "https://placehold.co/800x800/222/white?text=Bell+MX-9+Adventure+MIPS+2",
        "https://placehold.co/800x800/222/white?text=Bell+MX-9+Adventure+MIPS+3"
    ],
    "features_data": {
        "visor": [
            "Pinlock Ready",
            "Integrated Sun Visor"
        ]
    },
    "tech_integration": {
        "comms_cutout_type": "Generic Speaker Cutouts"
    }
}