{
    "id": "ckx_tx696",
    "entity": "helmet",
    "title": "CKX TX696",
    "brand": "CKX",
    "type": "Dirt / MX",
    "helmet_family": "TX696",
    "price": {
        "current": 179.99,
        "currency": "USD"
    },
    "head_shape": "Intermediate Oval",
    "specs": {
        "material": "Polycarbonate",
        "weight_g": 1350,
        "weight_lbs": 2.98,
        "certifications": [
            "DOT"
        ],
        "warranty_years": 1,
        "strap_type": "Double D-Ring"
    },
    "description": "Four-season off-road with electric shield and dual-sport capability.",
    "product_details": {
        "description": "Four-season off-road with electric shield and dual-sport capability."
    },
    "variants": [
        {
            "id": "ckx_tx696_gloss-black",
            "entity": "helmet",
            "title": "CKX TX696 Gloss Black",
            "type": "Dirt / MX",
            "parent_id": "ckx_tx696",
            "helmet_family": "TX696",
            "head_shape": "Intermediate Oval",
            "color": "Gloss Black",
            "color_family": "Black",
            "sku": "CKX-TX69-BLK",
            "finish": "gloss",
            "is_graphic": false,
            "availability": "instock",
            "description": "Four-season off-road with electric shield and dual-sport capability.",
            "product_details": {
                "description": "Four-season off-road with electric shield and dual-sport capability."
            },
            "price": {
                "current": 179.99,
                "usd": 179.99,
                "eur": 165.59,
                "gbp": 142.19
            },
            "specs": {
                "material": "Polycarbonate",
                "weight_g": 1350,
                "weight_lbs": 2.98,
                "certifications": [
                    "DOT"
                ]
            },
            "geo_media": [
                "https://placehold.co/800x800/222/white?text=CKX+TX696+Gloss+Black",
                "https://placehold.co/800x800/222/white?text=CKX+TX696+Gloss+Black+Side",
                "https://placehold.co/800x800/222/white?text=CKX+TX696+Gloss+Black+Back"
            ],
            "helmet_types": [
                "Dirt / MX"
            ]
        },
        {
            "id": "ckx_tx696_anthracite",
            "entity": "helmet",
            "title": "CKX TX696 Anthracite",
            "type": "Dirt / MX",
            "parent_id": "ckx_tx696",
            "helmet_family": "TX696",
            "head_shape": "Intermediate Oval",
            "color": "Anthracite",
            "color_family": "Grey",
            "sku": "CKX-TX69-GRE",
            "finish": "matte",
            "is_graphic": false,
            "availability": "instock",
            "description": "Four-season off-road with electric shield and dual-sport capability.",
            "product_details": {
                "description": "Four-season off-road with electric shield and dual-sport capability."
            },
            "price": {
                "current": 179.99,
                "usd": 179.99,
                "eur": 165.59,
                "gbp": 142.19
            },
            "specs": {
                "material": "Polycarbonate",
                "weight_g": 1350,
                "weight_lbs": 2.98,
                "certifications": [
                    "DOT"
                ]
            },
            "geo_media": [
                "https://placehold.co/800x800/222/white?text=CKX+TX696+Anthracite",
                "https://placehold.co/800x800/222/white?text=CKX+TX696+Anthracite+Side",
                "https://placehold.co/800x800/222/white?text=CKX+TX696+Anthracite+Back"
            ],
            "helmet_types": [
                "Dirt / MX"
            ]
        },
        {
            "id": "ckx_tx696_solid-grey",
            "entity": "helmet",
            "title": "CKX TX696 Solid Grey",
            "type": "Dirt / MX",
            "parent_id": "ckx_tx696",
            "helmet_family": "TX696",
            "head_shape": "Intermediate Oval",
            "color": "Solid Grey",
            "color_family": "Grey",
            "sku": "CKX-TX69-SOL",
            "finish": "matte",
            "is_graphic": true,
            "availability": "instock",
            "description": "Four-season off-road with electric shield and dual-sport capability.",
            "product_details": {
                "description": "Four-season off-road with electric shield and dual-sport capability."
            },
            "price": {
                "current": 229.99,
                "usd": 229.99,
                "eur": 211.59,
                "gbp": 181.69
            },
            "specs": {
                "material": "Polycarbonate",
                "weight_g": 1350,
                "weight_lbs": 2.98,
                "certifications": [
                    "DOT"
                ]
            },
            "geo_media": [
                "https://placehold.co/800x800/222/white?text=CKX+TX696+Solid+Grey",
                "https://placehold.co/800x800/222/white?text=CKX+TX696+Solid+Grey+Side",
                "https://placehold.co/800x800/222/white?text=CKX+TX696+Solid+Grey+Back"
            ],
            "helmet_types": [
                "Dirt / MX"
            ]
        },
        {
            "id": "ckx_tx696_flow-grey",
            "entity": "helmet",
            "title": "CKX TX696 Flow Grey",
            "type": "Dirt / MX",
            "parent_id": "ckx_tx696",
            "helmet_family": "TX696",
            "head_shape": "Intermediate Oval",
            "color": "Flow Grey",
            "color_family": "Grey",
            "sku": "CKX-TX69-FLO",
            "finish": "matte",
            "is_graphic": true,
            "availability": "instock",
            "description": "Four-season off-road with electric shield and dual-sport capability.",
            "product_details": {
                "description": "Four-season off-road with electric shield and dual-sport capability."
            },
            "price": {
                "current": 229.99,
                "usd": 229.99,
                "eur": 211.59,
                "gbp": 181.69
            },
            "specs": {
                "material": "Polycarbonate",
                "weight_g": 1350,
                "weight_lbs": 2.98,
                "certifications": [
                    "DOT"
                ]
            },
            "geo_media": [
                "https://placehold.co/800x800/222/white?text=CKX+TX696+Flow+Grey",
                "https://placehold.co/800x800/222/white?text=CKX+TX696+Flow+Grey+Side",
                "https://placehold.co/800x800/222/white?text=CKX+TX696+Flow+Grey+Back"
            ],
            "helmet_types": [
                "Dirt / MX"
            ]
        }
    ],
    "geo_media": [
        "https://placehold.co/800x800/222/white?text=CKX+TX696+1",
        "https://placehold.co/800x800/222/white?text=CKX+TX696+2",
        "https://placehold.co/800x800/222/white?text=CKX+TX696+3"
    ],
    "features_data": {
        "visor": [
            "Pinlock Ready",
            "Optically Correct"
        ]
    },
    "tech_integration": {
        "comms_cutout_type": "Generic Speaker Cutouts"
    }
}