{
    "id": "gmax_mx_46y",
    "entity": "helmet",
    "title": "GMax MX-46Y",
    "brand": "GMax",
    "type": "Dirt / MX",
    "helmet_family": "MX-46Y",
    "price": {
        "current": 69.95,
        "currency": "USD"
    },
    "head_shape": "Intermediate Oval",
    "specs": {
        "material": "Polycarbonate",
        "weight_g": 1100,
        "weight_lbs": 2.43,
        "certifications": [
            "DOT",
            "ECE 22.06"
        ]
    },
    "description": "Youth-sized MX helmet with adjustable visor and washable liner.",
    "product_details": {
        "description": "Youth-sized MX helmet with adjustable visor and washable liner."
    },
    "variants": [
        {
            "id": "gmax_mx_46y_gloss-black",
            "entity": "helmet",
            "title": "GMax MX-46Y Gloss Black",
            "type": "Dirt / MX",
            "parent_id": "gmax_mx_46y",
            "helmet_family": "MX-46Y",
            "head_shape": "Intermediate Oval",
            "color": "Gloss Black",
            "color_family": "Black",
            "sku": "GMA-MX46-BLK",
            "finish": "gloss",
            "is_graphic": false,
            "availability": "instock",
            "description": "Youth-sized MX helmet with adjustable visor and washable liner.",
            "product_details": {
                "description": "Youth-sized MX helmet with adjustable visor and washable liner."
            },
            "price": {
                "current": 69.95,
                "usd": 69.95,
                "eur": 64.35,
                "gbp": 55.26
            },
            "specs": {
                "material": "Polycarbonate",
                "weight_g": 1100,
                "weight_lbs": 2.43,
                "certifications": [
                    "DOT",
                    "ECE 22.06"
                ]
            },
            "geo_media": [
                "https://placehold.co/800x800/222/white?text=GMax+MX-46Y+Gloss+Black",
                "https://placehold.co/800x800/222/white?text=GMax+MX-46Y+Gloss+Black+Side",
                "https://placehold.co/800x800/222/white?text=GMax+MX-46Y+Gloss+Black+Back"
            ],
            "helmet_types": [
                "Dirt / MX"
            ]
        },
        {
            "id": "gmax_mx_46y_pearl-white",
            "entity": "helmet",
            "title": "GMax MX-46Y Pearl White",
            "type": "Dirt / MX",
            "parent_id": "gmax_mx_46y",
            "helmet_family": "MX-46Y",
            "head_shape": "Intermediate Oval",
            "color": "Pearl White",
            "color_family": "White",
            "sku": "GMA-MX46-WHI",
            "finish": "gloss",
            "is_graphic": false,
            "availability": "instock",
            "description": "Youth-sized MX helmet with adjustable visor and washable liner.",
            "product_details": {
                "description": "Youth-sized MX helmet with adjustable visor and washable liner."
            },
            "price": {
                "current": 69.95,
                "usd": 69.95,
                "eur": 64.35,
                "gbp": 55.26
            },
            "specs": {
                "material": "Polycarbonate",
                "weight_g": 1100,
                "weight_lbs": 2.43,
                "certifications": [
                    "DOT",
                    "ECE 22.06"
                ]
            },
            "geo_media": [
                "https://placehold.co/800x800/222/white?text=GMax+MX-46Y+Pearl+White",
                "https://placehold.co/800x800/222/white?text=GMax+MX-46Y+Pearl+White+Side",
                "https://placehold.co/800x800/222/white?text=GMax+MX-46Y+Pearl+White+Back"
            ],
            "helmet_types": [
                "Dirt / MX"
            ]
        },
        {
            "id": "gmax_mx_46y_gloss-white",
            "entity": "helmet",
            "title": "GMax MX-46Y Gloss White",
            "type": "Dirt / MX",
            "parent_id": "gmax_mx_46y",
            "helmet_family": "MX-46Y",
            "head_shape": "Intermediate Oval",
            "color": "Gloss White",
            "color_family": "White",
            "sku": "GMA-MX46-WHI",
            "finish": "gloss",
            "is_graphic": false,
            "availability": "instock",
            "description": "Youth-sized MX helmet with adjustable visor and washable liner.",
            "product_details": {
                "description": "Youth-sized MX helmet with adjustable visor and washable liner."
            },
            "price": {
                "current": 69.95,
                "usd": 69.95,
                "eur": 64.35,
                "gbp": 55.26
            },
            "specs": {
                "material": "Polycarbonate",
                "weight_g": 1100,
                "weight_lbs": 2.43,
                "certifications": [
                    "DOT",
                    "ECE 22.06"
                ]
            },
            "geo_media": [
                "https://placehold.co/800x800/222/white?text=GMax+MX-46Y+Gloss+White",
                "https://placehold.co/800x800/222/white?text=GMax+MX-46Y+Gloss+White+Side",
                "https://placehold.co/800x800/222/white?text=GMax+MX-46Y+Gloss+White+Back"
            ],
            "helmet_types": [
                "Dirt / MX"
            ]
        },
        {
            "id": "gmax_mx_46y_urban-tc-5",
            "entity": "helmet",
            "title": "GMax MX-46Y Urban TC-5",
            "type": "Dirt / MX",
            "parent_id": "gmax_mx_46y",
            "helmet_family": "MX-46Y",
            "head_shape": "Intermediate Oval",
            "color": "Urban TC-5",
            "color_family": "Multi",
            "sku": "GMA-MX46-URB",
            "finish": "gloss",
            "is_graphic": true,
            "availability": "instock",
            "description": "Youth-sized MX helmet with adjustable visor and washable liner.",
            "product_details": {
                "description": "Youth-sized MX helmet with adjustable visor and washable liner."
            },
            "price": {
                "current": 119.95,
                "usd": 119.95,
                "eur": 110.35,
                "gbp": 94.76
            },
            "specs": {
                "material": "Polycarbonate",
                "weight_g": 1100,
                "weight_lbs": 2.43,
                "certifications": [
                    "DOT",
                    "ECE 22.06"
                ]
            },
            "geo_media": [
                "https://placehold.co/800x800/222/white?text=GMax+MX-46Y+Urban+TC-5",
                "https://placehold.co/800x800/222/white?text=GMax+MX-46Y+Urban+TC-5+Side",
                "https://placehold.co/800x800/222/white?text=GMax+MX-46Y+Urban+TC-5+Back"
            ],
            "helmet_types": [
                "Dirt / MX"
            ]
        }
    ],
    "geo_media": [
        "https://placehold.co/800x800/222/white?text=GMax+MX-46Y+1",
        "https://placehold.co/800x800/222/white?text=GMax+MX-46Y+2",
        "https://placehold.co/800x800/222/white?text=GMax+MX-46Y+3"
    ]
}