{
    "id": "gmax_mx_46y_urban-tc-5",
    "entity": "helmet",
    "title": "GMax MX-46Y Urban TC-5",
    "brand": "GMax",
    "type": "Dirt / MX",
    "helmet_types": [
        "Dirt / MX"
    ],
    "parent_id": "gmax_mx_46y",
    "helmet_family": "MX-46Y",
    "price": {
        "current": 119.95,
        "usd": 119.95,
        "eur": 110.35,
        "gbp": 94.76
    },
    "certifications": [
        "DOT"
    ],
    "head_shape": "Intermediate Oval",
    "specs": {
        "material": "Polycarbonate",
        "weight_g": 1100,
        "weight_lbs": 2.43,
        "certifications": [
            "DOT"
        ],
        "warranty_years": 1,
        "strap_type": "Double D-Ring"
    },
    "description": "Youth-sized MX helmet with adjustable visor and washable liner.",
    "product_details": {
        "description": "Youth-sized MX helmet with adjustable visor and washable liner."
    },
    "geo_media": [
        "https://placehold.co/800x800/222/white?text=GMax+MX-46Y+Urban+TC-5",
        "https://placehold.co/800x800/222/white?text=GMax+MX-46Y+Urban+TC-5+Side",
        "https://placehold.co/800x800/222/white?text=GMax+MX-46Y+Urban+TC-5+Back"
    ],
    "color": "Urban TC-5",
    "color_family": "Multi",
    "sku": "GMA-MX46-URB",
    "finish": "gloss",
    "is_graphic": true,
    "availability": "instock",
    "features_data": {
        "visor": [
            "Pinlock Ready",
            "Optically Correct"
        ]
    },
    "tech_integration": {
        "comms_cutout_type": "Generic Speaker Cutouts"
    }
}