{
    "id": "hjc_cs_r3_silver-metallic",
    "entity": "helmet",
    "title": "HJC CS-R3 Silver Metallic",
    "brand": "HJC",
    "type": "Full Face",
    "helmet_types": [
        "Full Face"
    ],
    "parent_id": "hjc_cs_r3",
    "helmet_family": "CS-R3",
    "price": {
        "current": 139.99,
        "usd": 139.99,
        "eur": 128.79,
        "gbp": 110.59
    },
    "certifications": [
        "DOT"
    ],
    "head_shape": "Intermediate Oval",
    "specs": {
        "material": "Polycarbonate",
        "weight_g": 1600,
        "weight_lbs": 3.53,
        "certifications": [
            "DOT"
        ],
        "warranty_years": 1,
        "strap_type": "Double D-Ring",
        "shell_sizes_count": 2
    },
    "description": "Budget-friendly street helmet with proven reliability.",
    "product_details": {
        "description": "Budget-friendly street helmet with proven reliability."
    },
    "geo_media": [
        "https://placehold.co/800x800/222/white?text=HJC+CS-R3+Silver+Metallic",
        "https://placehold.co/800x800/222/white?text=HJC+CS-R3+Silver+Metallic+Side",
        "https://placehold.co/800x800/222/white?text=HJC+CS-R3+Silver+Metallic+Back"
    ],
    "color": "Silver Metallic",
    "color_family": "Grey",
    "sku": "HJC-CSR3-GRE",
    "finish": "gloss",
    "is_graphic": false,
    "availability": "instock",
    "features_data": {
        "visor": [
            "Pinlock Ready",
            "Optically Correct"
        ]
    },
    "tech_integration": {
        "comms_cutout_type": "Generic Speaker Cutouts",
        "speaker_pocket_depth_mm": 35,
        "cable_management": true
    },
    "model_year": 2018,
    "identifiers": {
        "asin": "B07Q2X8V3K",
        "ean": "4965118000000",
        "mpn": "CS-R3-SILVER-METALLIC"
    },
    "safety_intelligence": {
        "homologation_standard": "ECE 22.05",
        "sharp_rating": 4,
        "rotational_mitigation": true
    },
    "sizing_fit": {
        "fit_notes": "Designed for oval to intermediate head shapes; may feel tight on very round heads due to aggressive cheek padding.",
        "head_shape": "Oval/Intermediate"
    },
    "deep_enriched": true
}