{
    "id": "ls2_thunder_blue",
    "entity": "helmet",
    "title": "LS2 Thunder Blue",
    "brand": "LS2",
    "type": "Full Face",
    "helmet_types": [
        "Full Face"
    ],
    "parent_id": "ls2_thunder",
    "helmet_family": "Thunder",
    "price": {
        "current": 119.99,
        "usd": 119.99,
        "eur": 110.39,
        "gbp": 94.79
    },
    "certifications": [
        "DOT",
        "ECE 22.05"
    ],
    "head_shape": "Intermediate Oval",
    "specs": {
        "material": "Polycarbonate",
        "weight_g": 1580,
        "weight_lbs": 3.48,
        "certifications": [
            "DOT",
            "ECE 22.05"
        ],
        "warranty_years": 2,
        "strap_type": "Double D-Ring",
        "shell_sizes_count": 3
    },
    "description": "Entry-level full face with good ventilation and removable liner.",
    "product_details": {
        "description": "Entry-level full face with good ventilation and removable liner."
    },
    "geo_media": [
        "https://placehold.co/800x800/222/white?text=LS2+Thunder+Blue",
        "https://placehold.co/800x800/222/white?text=LS2+Thunder+Blue+Side",
        "https://placehold.co/800x800/222/white?text=LS2+Thunder+Blue+Back"
    ],
    "color": "Blue",
    "color_family": "Blue",
    "sku": "LS2-THN-BLU",
    "finish": "gloss",
    "is_graphic": false,
    "availability": "instock",
    "features_data": {
        "visor": [
            "Pinlock Ready",
            "Optically Correct"
        ]
    },
    "tech_integration": {
        "comms_cutout_type": "Generic Speaker Cutouts"
    }
}