{
    "id": "nolan_n21_visor_gloss-black",
    "entity": "helmet",
    "title": "Nolan N21 Visor Gloss Black",
    "brand": "Nolan",
    "type": "Open Face",
    "helmet_types": [
        "Open Face"
    ],
    "parent_id": "nolan_n21_visor",
    "helmet_family": "N21 Visor",
    "price": {
        "current": 199.99,
        "usd": 199.99,
        "eur": 183.99,
        "gbp": 157.99
    },
    "certifications": [
        "ECE 22.06"
    ],
    "head_shape": "Intermediate Oval",
    "specs": {
        "material": "Polycarbonate",
        "weight_g": 1100,
        "weight_lbs": 2.43,
        "certifications": [
            "ECE 22.06"
        ],
        "warranty_years": 2,
        "strap_type": "Double D-Ring",
        "shell_sizes_count": 1
    },
    "description": "Urban open face with integrated visor and N-Com communication ready.",
    "product_details": {
        "description": "Urban open face with integrated visor and N-Com communication ready."
    },
    "geo_media": [
        "https://placehold.co/800x800/222/white?text=Nolan+N21+Visor+Gloss+Black",
        "https://placehold.co/800x800/222/white?text=Nolan+N21+Visor+Gloss+Black+Side",
        "https://placehold.co/800x800/222/white?text=Nolan+N21+Visor+Gloss+Black+Back"
    ],
    "color": "Gloss Black",
    "color_family": "Black",
    "sku": "NOL-N21V-BLK",
    "finish": "gloss",
    "is_graphic": false,
    "availability": "instock",
    "features_data": {
        "visor": [
            "Pinlock Ready",
            "Optically Correct"
        ]
    },
    "tech_integration": {
        "comms_cutout_type": "Generic Speaker Cutouts",
        "speaker_pocket_depth_mm": 35,
        "cable_management": true
    },
    "model_year": 2018,
    "identifiers": {
        "asin": "B07Q2K3V8X",
        "ean": "8059461000000",
        "mpn": "N21-GB"
    },
    "safety_intelligence": {
        "homologation_standard": "ECE 22.05",
        "sharp_rating": 5,
        "rotational_mitigation": true
    },
    "sizing_fit": {
        "fit_notes": "Designed for open-face fit; offers a secure fit for most head shapes but may feel tight on very large occipital lobes due to the visor mechanism.",
        "head_shape": "Universal"
    },
    "deep_enriched": true
}