{
    "id": "scorpion_exo_r420_silver-metallic",
    "entity": "helmet",
    "title": "Scorpion EXO-R420 Silver Metallic",
    "brand": "Scorpion",
    "type": "Full Face",
    "helmet_types": [
        "Full Face"
    ],
    "parent_id": "scorpion_exo_r420",
    "helmet_family": "EXO-R420",
    "price": {
        "current": 159.95,
        "usd": 159.95,
        "eur": 147.15,
        "gbp": 126.36
    },
    "certifications": [
        "DOT",
        "Snell M2020"
    ],
    "head_shape": "Intermediate Oval",
    "specs": {
        "material": "Polycarbonate",
        "weight_g": 1620,
        "weight_lbs": 3.57,
        "certifications": [
            "DOT",
            "Snell M2020"
        ],
        "warranty_years": 2,
        "strap_type": "Double D-Ring",
        "shell_sizes_count": 4
    },
    "description": "Incredible value \u2014 Snell M2020 and DOT certified at an entry-level price.",
    "product_details": {
        "description": "Incredible value \u2014 Snell M2020 and DOT certified at an entry-level price."
    },
    "geo_media": [
        "https://placehold.co/800x800/222/white?text=Scorpion+EXO-R420+Silver+Metallic",
        "https://placehold.co/800x800/222/white?text=Scorpion+EXO-R420+Silver+Metallic+Side",
        "https://placehold.co/800x800/222/white?text=Scorpion+EXO-R420+Silver+Metallic+Back"
    ],
    "color": "Silver Metallic",
    "color_family": "Grey",
    "sku": "SCO-EXOR-GRE",
    "finish": "gloss",
    "is_graphic": false,
    "availability": "instock",
    "features_data": {
        "visor": [
            "Pinlock Ready",
            "Optically Correct"
        ]
    },
    "tech_integration": {
        "comms_cutout_type": "Generic Speaker Cutouts",
        "speaker_pocket_depth_mm": 35,
        "cable_management": true
    },
    "model_year": 2019,
    "identifiers": {
        "asin": "B07QKZV8JX",
        "ean": "841523069420",
        "mpn": "R420-SILVER-METALLIC"
    },
    "safety_intelligence": {
        "homologation_standard": "ECE 22.06",
        "sharp_rating": 5,
        "rotational_mitigation": true
    },
    "sizing_fit": {
        "fit_notes": "Designed for oval to intermediate head shapes; may feel tight on very round heads.",
        "head_shape": "Oval"
    },
    "deep_enriched": true
}