{
    "id": "studds_scramble_d4_matte-black",
    "entity": "helmet",
    "title": "Studds Scramble D4 Matte Black",
    "brand": "Studds",
    "type": "Dirt / MX",
    "helmet_types": [
        "Dirt / MX"
    ],
    "parent_id": "studds_scramble_d4",
    "helmet_family": "Scramble D4",
    "price": {
        "current": 52.99,
        "usd": 52.99,
        "eur": 48.75,
        "gbp": 41.86
    },
    "certifications": [
        "DOT"
    ],
    "head_shape": "Intermediate Oval",
    "specs": {
        "material": "ABS",
        "weight_g": 1280,
        "weight_lbs": 2.82,
        "certifications": [
            "DOT"
        ],
        "warranty_years": 1,
        "strap_type": "Double D-Ring"
    },
    "description": "Off-road helmet with peak and goggles-ready design for Indian roads.",
    "product_details": {
        "description": "Off-road helmet with peak and goggles-ready design for Indian roads."
    },
    "geo_media": [
        "https://placehold.co/800x800/222/white?text=Studds+Scramble+D4+Matte+Black",
        "https://placehold.co/800x800/222/white?text=Studds+Scramble+D4+Matte+Black+Side",
        "https://placehold.co/800x800/222/white?text=Studds+Scramble+D4+Matte+Black+Back"
    ],
    "color": "Matte Black",
    "color_family": "Black",
    "sku": "STU-SCR-BLK",
    "finish": "matte",
    "is_graphic": false,
    "availability": "instock",
    "features_data": {
        "visor": [
            "Pinlock Ready",
            "Optically Correct"
        ]
    },
    "tech_integration": {
        "comms_cutout_type": "Generic Speaker Cutouts"
    }
}